[
    { "customer": "AUTOLIV INDIA PVT LTD", "output": 32050, "percent": 10 },
    { "customer": "AUTOLIV INDIA PVT LTD.", "output": 64173, "percent": 10 },
    { "customer": "Hyundai Mobis India Limited", "output": 1295, "percent": 5 },
    { "customer": "Joysonsafety", "output": 71231, "percent": 10 },
    { "customer": "Magneti Marelli Motherson Auto System", "output": 168, "percent": 2 },
    { "customer": "Valeo-India", "output": 7208, "percent": 20 },
    { "customer": "ZF Rane", "output": 26225, "percent": 7 },
    { "customer": "Mahle", "output": 2945, "percent": 11 },
    { "customer": "Interface", "output": 1800, "percent": 8 },
    { "customer": "ITW", "output": 0, "percent": 0 },
    { "customer": "ICHIKOH INDUSTRIES", "output": 0, "percent": 0 },
    { "customer": "Sanden Vikas", "output": 0, "percent": 0 },
    { "customer": "TATA", "output": 1632, "percent": 14 },
    { "customer": "Tata Ficosa", "output": 4200, "percent": 6 },
    { "customer": "TATA MAGNA", "output": 1525, "percent": 11 },
    { "customer": "MSKH SEATING SYSTEMS", "output": 1116, "percent": 4 },
    { "customer": "Magna", "output": 540, "percent": 10 },
    { "customer": "Varroc", "output": 5364, "percent": 8 }
]